hwp/__init__.py
hwp/hello.py
helloasdfg1234-0.0.1.dist-info/METADATA
helloasdfg1234-0.0.1.dist-info/WHEEL
helloasdfg1234-0.0.1.dist-info/top_level.txt
helloasdfg1234-0.0.1.dist-info/RECORD
