Metadata-Version: 2.1
Name: helloasdfg1234
Version: 0.0.1
Summary: A basic Hello package
Home-page: UNKNOWN
Author: 314amruta349043
Author-email: ap8112002@gmail.com
License: UNKNOWN
Keywords: python
Platform: UNKNOWN
Classifier: Development Status :: 1 - Planning
Classifier: Intended Audience :: Developers
Classifier: Programming Language :: Python :: 3
Classifier: Operating System :: Unix
Classifier: Operating System :: MacOS :: MacOS X
Classifier: Operating System :: Microsoft :: Windows
